{"user_id": "2026797305", "username": "@cuocdoivandep", "coins": 74007129704695, "exp": 14595910318, "total_exp": 14595910318, "level": 342, "fishing_count": 156186, "win_count": 156186, "lose_count": 0, "chanle_win": 5, "chanle_lose": 5, "owned_rods": ["1", "4", "4", "7", "7", "10", "13", "8", "9", "11", "12", "14", "2", "3", "5", "6", "15", "16", "17", "18", "19", "20"], "inventory": {"rod": "20", "fish": {"๐ Cรก thแบงn tiรชn": 1, "๐ Cรก mแปi 28": 1, "๐ Cรก mแปi 24": 2, "๐ Cรก mแปi 2": 1, "๐ข Rรนa biแปn": 1, "๐ Cรก trฤng": 1, "๐ฆช Hรu": 2, "๐ Cรก mแปi 48": 1, "๐ Cรก vรng": 1, "๐ฆ Tรดm sรบ": 2, "๐ช Cรก hรnh tinh": 1, "๐ Cรก mแปi 25": 1, "๐ Cรก mแปi 16": 1, "๐ Cรก ngรขn hร": 1, "๐ Cรก mแปi 26": 1, "โฐ๏ธ Cรก ฤรก": 1, "๐ Cรก hแบฏc รกm": 1, "๐ Cรก cแบงu vแปng": 1, "๐ Cรก mแปi 11": 1, "๐ Cรก Bรญ แบจn 80": 70, "โพ๏ธ Cรก Hฦฐ Khรดng": 75, "๐ Cรก Bรญ แบจn 111": 86, "๐ฆ Cรก Vแบนt Biแปn": 95, "๐ Cรก Bรญ แบจn 74": 69, "โ๏ธ Cรก Bฤng Kแปณ Lรขn": 90, "๐ Cรก Tแปi Thฦฐแปฃng": 78, "๐ Cรก Bรญ แบจn 67": 80, "๐ Cรก Bรญ แบจn 91": 74, "๐ฆด Cรก Xฦฐฦกng Trแบฏng": 80, "๐ฆข Cรก Thiรชn Nga": 77, "๐ Cรก Bรญ แบจn 86": 79, "๐ Cรก Bรญ แบจn 101": 86, "๐ Cรก Bรญ แบจn 88": 89, "๐ Cรก Ngแบกc Long": 80, "๐ Cรก Bรญ แบจn 92": 70, "๐ Cรก Bรญ แบจn 105": 75, "๐ Cรก Bรญ แบจn 97": 67, "๐ Cรก Bรญ แบจn 104": 74, "๐ Cรก Bรญ แบจn 65": 69, "๐ Cรก Bรญ แบจn 96": 80, "๐ซ Cรก Tinh Vรขn": 91, "๐ฑ Cรก Thแปงy Thแบงn": 81, "๐ Cรก Bรญ แบจn 71": 82, "๐ Cรก Bรญ แบจn 89": 80, "๐ Cรก Bรญ แบจn 75": 86, "๐ Cรก Bแบกch Ma": 84, "๐ Cรก Bรญ แบจn 95": 90, "๐ฆช Cรก Ngแปc Trai": 89, "๐ Cรก Bรญ แบจn 83": 67, "โญ Cรก Sรกng Tแบกo": 74, "๐ Cรก Voi Thแบงn": 91, "๐ Cรก Vลฉ Trแปฅ": 67, "๐ Cรก Hแบฃi Hoรng": 81, "๐ Cรก Bรญ แบจn 90": 90, "๐ Cรก Bรญ แบจn 72": 82, "๐ Cรก Thแบงn Thoแบกi": 78, "๐ Cรก Bรญ แบจn 66": 76, "๐ Cรก Bรญ แบจn 103": 76, "๐ Cรก Thแบงn Long": 84, "๐ Cรก Chรบa Tแป": 77, "๐ Cรก Bรญ แบจn 108": 78, "๐ฆ Cรก Tรดm ฤแป": 89, "โก Cรก Lรดi Long": 82, "๐ Cรก Bรญ แบจn 85": 97, "๐ Cรก Bรญ แบจn 68": 95, "๐ฆฆ Cรก Linh Hoแบกt": 78, "๐ Cรก Bรญ แบจn 94": 83, "๐ Cรก Bรญ แบจn 84": 96, "๐ Cรก Kim Hoa": 77, "๐ฆ Cรก Hแป Phรกch": 90, "๐ Cรก Thiรชn Tiรชn": 96, "โพ๏ธ Cรก Tแปi Hแบญu": 47, "๐ฅ Cรก Hแปa Phแปฅng": 98, "๐ Cรก Bรญ แบจn 82": 89, "๐ Cรก Kim Cฦฐฦกng": 88, "๐ Cรก Bรญ แบจn 81": 78, "๐ Cรก Bรญ แบจn 93": 78, "๐ฎ Cรก Hฦฐ Khรดng": 85, "๐ค Cรก Tรฉp Dรขn Dรฃ": 91, "๐ Cรก Vแป Ngแปc": 74, "๐ฆ Cรก Mแปฑc ฤรชm": 87, "๐ฆ Cรก Mแบญp Biแปn": 74, "๐ Cรก Bรญ แบจn 78": 92, "๐ Cรก Bรณng Ma": 4, "๐ฆ Cรก แปng Mแปฑc": 90, "๐ Cรก Bรญ แบจn 62": 94, "๐ Cรก Vฤฉnh Hแบฑng": 90, "๐ก Cรก ฤแปc Tแป": 72, "๐ Cรก Bรญ แบจn 69": 81, "๐ Cรก Bรญ แบจn 99": 86, "๐ฆฉ Cรก Hแบกc Hแปng": 97, "๐ Cรก Nhi ฤแปng": 81, "๐ฆญ Cรก Hแบฃi Hแปn": 76, "๐ข Cรก Quy Thแปงy": 80, "๐ Cรก Bรญ แบจn 109": 65, "๐ Cรก Bรญ แบจn 107": 85, "๐ Cรก Bรญ แบจn 70": 83, "๐ Cรก Hแบฃi Vฦฐฦกng": 81, "๐ Cรก Bรญ แบจn 102": 79, "๐ฆ Cรก Hรนm Biแปn": 72, "๐ Cรก Bรญ แบจn 76": 92, "๐ซ Cรก Thแบงn Quang": 8, "๐ฆ Cua Giรกp Ngแปc": 91, "๐ Cรก Tuyแปt ฤแปnh": 10, "๐ Cรก Bรญ แบจn 77": 87, "๐ Cรก Bรญ แบจn 73": 95, "๐ Cรก Bรญ แบจn 63": 90, "๐ Cรก Bรญ แบจn 51": 3, "๐ Cรก Bรญ แบจn 87": 84, "๐ Cรก Bรญ แบจn 79": 89, "๐ฎ Cรก Ma Phรกp": 15, "๐ Cรก Bรญ แบจn 106": 76, "๐ Cรก Bรญ แบจn 64": 80, "๐ Cรก Bรญ แบจn 110": 89, "๐ Cรก Bรญ แบจn 98": 92, "๐ฎ Cรก Bรญ แบจn": 18, "๐ Cรก Bรญ แบจn 100": 71, "โพ๏ธ Cรก Vรด Cแปฑc": 56, "๐ Cรก Bรญ แบจn 52": 2, "๐ Cรก Tแปi Thฦฐแปฃng": 13, "๐ Cรก Bรญ แบจn 56": 1, "๐ Cรก Bรญ แบจn 53": 3, "๐ Cรก Bรญ แบจn 54": 1, "๐ Cรก Bรญ แบจn 57": 1}}, "created_at": "2025-08-23T17:28:06.069812", "level_exp": 357845796}
{"user_id": "6951525095", "username": "@Cubicutcho44", "coins": 124760263, "exp": 525145, "total_exp": 525145, "level": 90, "level_exp": 23595, "fishing_count": 7664, "win_count": 7664, "lose_count": 0, "chanle_win": 0, "chanle_lose": 0, "owned_rods": ["1", "6", "7", "8", "9", "10", "11", "12", "12", "13", "5"], "inventory": {"rod": "13", "fish": {"๐ข Rรนa biแปn": 27, "๐ฆด Xฦฐฦกng rแปng": 26, "๐ Sรฒ ฤiแปp": 31, "๐ฆ Tรดm sรบ": 38, "๐ฆ Tรดm": 34, "๐ Cรก nhแป": 32, "๐ฆญ Hแบฃi cแบฉu": 32, "๐ค Tรฉp": 41, "๐ฆ Mแปฑc": 33, "๐ฆ Cรก mแบญp": 26, "๐ก Cรก nรณc": 34, "๐ Cรก vรng": 29, "๐ฆช Hรu": 36, "๐ฆฉ Hแปng hแบกc": 13, "๐ฆ Tรดm hรนm": 11, "๐ฆ Mแปฑc แปng": 25, "๐ฆ Cua": 26, "๐ Cรก voi": 2, "๐ฆฆ Rรกi cรก": 12, "๐ฆ Vแบนt biแปn": 2, "๐ Cรก sแบฅu": 2, "๐ Cรก thแบงn tiรชn": 1, "๐ Bแบกch tuแปc": 7, "๐ Rแปng biแปn": 1, "๐ฆข Thiรชn nga": 5}}, "created_at": "2025-08-24T09:24:04.398141"}